MANIFEST.in
README
_version.py
setup.cfg
setup.py
doqu/__init__.py
doqu/backend_base.py
doqu/dist.py
doqu/document_base.py
doqu/document_base_new.py
doqu/future.py
doqu/validators.py
doqu.egg-info/PKG-INFO
doqu.egg-info/SOURCES.txt
doqu.egg-info/dependency_links.txt
doqu.egg-info/entry_points.txt
doqu.egg-info/requires.txt
doqu.egg-info/top_level.txt
doqu/ext/__init__.py
doqu/ext/forms.py
doqu/ext/fields/__init__.py
doqu/ext/fields/base.py
doqu/ext/fields/files.py
doqu/ext/mongodb/__init__.py
doqu/ext/mongodb/converters.py
doqu/ext/mongodb/lookups.py
doqu/ext/shelve_db/__init__.py
doqu/ext/shelve_db/converters.py
doqu/ext/shelve_db/lookups.py
doqu/ext/shove_db/__init__.py
doqu/ext/tokyo_cabinet/__init__.py
doqu/ext/tokyo_cabinet/converters.py
doqu/ext/tokyo_cabinet/lookups.py
doqu/ext/tokyo_tyrant/__init__.py
doqu/ext/tokyo_tyrant/converters.py
doqu/ext/tokyo_tyrant/lookups.py
doqu/ext/tokyo_tyrant/managers.py
doqu/ext/tokyo_tyrant/query.py
doqu/ext/tokyo_tyrant/storage.py
doqu/utils/__init__.py
doqu/utils/data_structures.py
doqu/validation/__init__.py