Metadata-Version: 1.1
Name: doqu
Version: 0.28.1
Summary: Document-query: models for schema-less databases.
Home-page: http://bitbucket.org/neithere/doqu/
Author: Andrey Mikhaylenko
Author-email: andy@neithere.net
License: GNU Lesser General Public License (LGPL), Version 3
Download-URL: http://bitbucket.org/neithere/doqu/src/
Keywords: document query database api model models orm key/value document-oriented non-relational tokyo cabinet mongodb
Platform: UNKNOWN
Classifier: Development Status :: 4 - Beta
Classifier: Environment :: Plugins
Classifier: Intended Audience :: Developers
Classifier: Intended Audience :: Education
Classifier: Intended Audience :: Information Technology
Classifier: Intended Audience :: Science/Research
Classifier: License :: OSI Approved :: GNU Library or Lesser General Public License (LGPL)
Classifier: Programming Language :: Python
Classifier: Topic :: Database
Classifier: Topic :: Database :: Database Engines/Servers
Classifier: Topic :: Database :: Front-Ends
Classifier: Topic :: Software Development :: Libraries :: Python Modules
Requires: python (>= 2.6)
Provides: doqu
Obsoletes: pymodels
Obsoletes: docu
